quantmsio/__init__.py
quantmsio/quantmsio_cli.py
quantmsio/commands/__init__.py
quantmsio/commands/absolute_expression_command.py
quantmsio/commands/attach_file_command.py
quantmsio/commands/convert_tsv_to_json_command.py
quantmsio/commands/diann_convert_command.py
quantmsio/commands/differential_expression_command.py
quantmsio/commands/feature_command.py
quantmsio/commands/generate_gene_msg_command.py
quantmsio/commands/generate_project_report_command.py
quantmsio/commands/generate_spectra_message_command.py
quantmsio/commands/generate_start_and_end_command.py
quantmsio/commands/get_unanimous_command.py
quantmsio/commands/load_best_scan_number_command.py
quantmsio/commands/parquet_to_json.py
quantmsio/commands/plot.py
quantmsio/commands/project_command.py
quantmsio/commands/psm_command.py
quantmsio/commands/statistics.py
quantmsio/core/__init__.py
quantmsio/core/ae.py
quantmsio/core/core.py
quantmsio/core/de.py
quantmsio/core/diann_convert.py
quantmsio/core/feature.py
quantmsio/core/feature_in_memory.py
quantmsio/core/json.py
quantmsio/core/mztab.py
quantmsio/core/openms.py
quantmsio/core/parquet_handler.py
quantmsio/core/plots.py
quantmsio/core/project.py
quantmsio/core/protein.py
quantmsio/core/psm.py
quantmsio/core/psm_in_memory.py
quantmsio/core/query.py
quantmsio/core/sdrf.py
quantmsio/core/statistics.py
quantmsio/core/tools.py
quantmsio/tests/__init__.py
quantmsio/tests/test_absoexp.py
quantmsio/tests/test_diffexp.py
quantmsio/tests/test_feature.py
quantmsio/tests/test_project.py
quantmsio/tests/test_psm.py
quantmsio/tests/test_sdrf.py
quantmsio/tests/test_spectra_msg.py
quantmsio/tests/test_statistics.py
quantmsio/utils/__init__.py
quantmsio/utils/constants.py
quantmsio/utils/file_utils.py
quantmsio/utils/pride_utils.py
quantmsio/utils/report.py
quantmsio-0.0.3.data/data/LICENSE
quantmsio-0.0.3.dist-info/LICENSE
quantmsio-0.0.3.dist-info/METADATA
quantmsio-0.0.3.dist-info/WHEEL
quantmsio-0.0.3.dist-info/entry_points.txt
quantmsio-0.0.3.dist-info/top_level.txt
quantmsio-0.0.3.dist-info/RECORD
