Metadata-Version: 2.1
Name: quantmsio
Version: 0.0.3
Summary: Convert multiple files into quantms.io format
Home-page: https://github.com/bigbio/quantms.io
Author: BigBio Team
Author-email: ypriverol@gmail.com
License: 'Apache 2.0
Keywords: python multiomics proteomics quantms reanalysis
Platform: any
Classifier: Programming Language :: Python :: 3
Classifier: License :: OSI Approved :: Apache Software License
Classifier: Operating System :: OS Independent
Classifier: Topic :: Scientific/Engineering :: Bio-Informatics
Requires-Python: >=3.6
License-File: LICENSE
Requires-Dist: click
Requires-Dist: pandas
Requires-Dist: requests
Requires-Dist: pytest
Requires-Dist: pyyaml
Requires-Dist: pyarrow
Requires-Dist: diskcache
Requires-Dist: pyopenms
Requires-Dist: scipy
Requires-Dist: biopython
Requires-Dist: seaborn
Requires-Dist: numpy
Requires-Dist: matplotlib
Requires-Dist: duckdb
Requires-Dist: mygene
Requires-Dist: pyahocorasick
Requires-Dist: swifter
Requires-Dist: ddt
Requires-Dist: psutil
